gates_by_universal_gates/and/and.v

module and_by_nand (
    y,a,b
);
    input a,b;
    output y;
    wire t1;
    nand_gate nand1(.a(a),.b(b),.y(t1));
    nand_gate nand2(.a(t1),.b(t1),.y(y));
endmodule

module and_by_nor (
    output y,input a,b
);
    wire t1,t2;
    nor_gate nor1(.a(a),.b(a),.y(t1));
    nor_gate nor2(.a(b),.b(b),.y(t2));
    nor_gate nor3(.a(t1),.b(t2),.y(y));
endmodule

module nor_gate (
    output y,input a,b
);
    supply1 vdd;
    supply0 gnd;
    wire p;
    //series pmos(drain,soure,gate)
    pmos (p,vdd,a);
    pmos (y,p,b);

    //parallel nmos(drain source gate)

    nmos(y,gnd,a);
    nmos(y,gnd,b);

endmodule


module nand_gate(output y, input a,b);
    supply1 vdd;
    supply0 gnd;
    
    wire n;
    //pmos(darin,source,gate)
    pmos s1(y,vdd,a);
    pmos s2(y,vdd,b);

    //nmos(drain,source,gate)
    nmos(n,gnd,b);
    nmos(y,n,a);
    
    
endmodule

gates_by_universal_gates/and/and_tb.v
module and_by_nand_nor();
    reg nand_a,nand_b,nor_a,nor_b;
    wire nand_y,nor_y;

    and_by_nand dut (.a(nand_a),.b(nand_b),.y(nand_y));

    and_by_nor uut(.a(nor_a),.b(nor_b),.y(nor_y));

    initial begin
        $dumpfile("wave.vcd");
        $dumpvars(0,and_by_nand_nor);
        $monitor("AND_BY_NAND ---  a: %b, b: %b, out: %b", nand_a, nand_b,
                     nand_y);
        nand_a=0; nand_b=0; #10;
        nand_a=0; nand_b=1; #10;
        nand_a=1; nand_b=0; #10;
        nand_a=1; nand_b=1; #10;
        $monitor("AND_BY_NOR ---  a: %b, b: %b, out: %b", nor_a, nor_b, nor_y);

        
        

        nor_a=0; nor_b=0; #10;
        nor_a=0; nor_b=1; #10;
        nor_a=1; nor_b=0; #10;
        nor_a=1; nor_b=1; #10;

        

        $finish;
    end
endmodule

gates_by_universal_gates/and/wave.vcd
$date
	Fri Apr 10 22:46:24 2026
$end
$version
	Icarus Verilog
$end
$timescale
	1s
$end
$scope module and_by_nand_nor $end
$var wire 1 ! nand_y $end
$var wire 1 " nor_y $end
$var reg 1 # nand_a $end
$var reg 1 $ nand_b $end
$var reg 1 % nor_a $end
$var reg 1 & nor_b $end
$scope module dut $end
$var wire 1 # a $end
$var wire 1 $ b $end
$var wire 1 ' t1 $end
$var wire 1 ! y $end
$scope module nand1 $end
$var wire 1 # a $end
$var wire 1 $ b $end
$var wire 1 ( gnd $end
$var wire 1 ) n $end
$var wire 1 * vdd $end
$var wire 1 ' y $end
$upscope $end
$scope module nand2 $end
$var wire 1 ' a $end
$var wire 1 ' b $end
$var wire 1 + gnd $end
$var wire 1 , n $end
$var wire 1 - vdd $end
$var wire 1 ! y $end
$upscope $end
$upscope $end
$scope module uut $end
$var wire 1 % a $end
$var wire 1 & b $end
$var wire 1 . t1 $end
$var wire 1 / t2 $end
$var wire 1 " y $end
$scope module nor1 $end
$var wire 1 % a $end
$var wire 1 % b $end
$var wire 1 0 gnd $end
$var wire 1 1 p $end
$var wire 1 2 vdd $end
$var wire 1 . y $end
$upscope $end
$scope module nor2 $end
$var wire 1 & a $end
$var wire 1 & b $end
$var wire 1 3 gnd $end
$var wire 1 4 p $end
$var wire 1 5 vdd $end
$var wire 1 / y $end
$upscope $end
$scope module nor3 $end
$var wire 1 . a $end
$var wire 1 / b $end
$var wire 1 6 gnd $end
$var wire 1 7 p $end
$var wire 1 8 vdd $end
$var wire 1 " y $end
$upscope $end
$upscope $end
$upscope $end
$enddefinitions $end
$comment Show the parameter values. $end
$dumpall
$end
#0
$dumpvars
18
x7
06
15
x4
03
12
x1
00
x/
x.
1-
0,
0+
1*
z)
0(
1'
x&
x%
0$
0#
x"
0!
$end
#10
0)
1$
#20
z)
0$
0,
0!
1'
1#
#30
z,
1!
0'
0)
1$
#40
14
1/
0&
0"
11
z7
1.
0%
#50
z4
0/
1&
#60
14
1/
0&
z1
17
0"
0.
1%
#70
z4
1"
0/
1&
