subractor/full_sub/full.v
module full_behavioural (
    a,b,c,diff,bor
);
    input a,b,c;
    output reg diff,bor;

    always @(*) begin
        diff = a^b^c;
        bor = ~a&b|~(a^b)&c;
    end
endmodule

module full_dataflow (
    a,b,c,diff,bor
);
    input a,b,c;
    output diff,bor;

    assign diff = a^b^c;
    assign bor = (~a&b)|~(a^b)&c;
endmodule

module full_gatelevel (
    a,b,c,diff,bor
);
    input a,b,c;
    output diff,bor;
    wire t1,t2,t3,t4;

    xor g1(t1,a,b);
    xor g2(diff,t1,c);
    not g3(t2,a);
    and g4(t3,t2,b);
    not g5(t4,t1);
    and g6(t5,t4,c);
    or g7(bor,t3,t5);
endmodule

subractor/full_sub/full_tb.v
module full_tb;
    reg a_b,b_b,c_b,a_d,b_d,c_d,a_g,b_g,c_g;
    wire diff_b,bor_b,diff_d,bor_d,diff_g,bor_g;

    full_behavioural dut_b(.a(a_b),.b(b_b),.c(c_b),.diff(diff_b),.bor(bor_b));
    full_dataflow dut_d(.a(a_d),.b(b_d),.c(c_d),.diff(diff_d),.bor(bor_d));
    full_gatelevel dut_g(.a(a_g),.b(b_g),.c(c_g),.diff(diff_g),.bor(bor_g));

    initial begin
        $dumpfile("full_output.vcd");
        $dumpvars(0,full_tb);
        $monitor("behavioural: a=%b  b=%b  c=%b  diff=%b   bor=%b", a_b,b_b,c_b,diff_b,bor_b);
        a_b=0; b_b=0; c_b=0; #10; 
        a_b=0; b_b=0; c_b=1; #10;   
        a_b=0; b_b=1; c_b=0; #10;   
        a_b=0; b_b=1; c_b=1; #10;    
        a_b=1; b_b=0; c_b=0; #10;  
        a_b=1; b_b=0; c_b=1; #10;   
        a_d=1; b_d=1; c_d=0; #10;   
        a_d=1; b_d=1; c_d=1; #10; 

        $monitor("dataflow: a=%b  b=%b  c=%b  diff=%b   bor=%b", a_d,b_d,c_d,diff_d,bor_d);
        a_d=0; b_d=0; c_d=0; #10;
        a_d=0; b_d=0; c_d=1; #10;
        a_d=0; b_d=1; c_d=0; #10;
        a_d=0; b_d=1; c_d=1; #10;
        a_d=1; b_d=0; c_d=0; #10;
        a_d=1; b_d=0; c_d=1; #10;
        a_d=1; b_d=1; c_d=0; #10;
        a_d=1; b_d=1; c_d=1; #10;
        $monitor("gatelevel: a=%b  b=%b  c=%b  diff=%b   bor=%b", a_g,b_g,c_g,diff_g,bor_g);
        a_g=0; b_g=0; c_g=0; #10;
        a_g=0; b_g=0; c_g=1; #10;
        a_g=0; b_g=1; c_g=0; #10;
        a_g=0; b_g=1; c_g=1; #10;
        a_g=1; b_g=0; c_g=0; #10;
        a_g=1; b_g=0; c_g=1; #10;
        a_g=1; b_g=1; c_g=0; #10;
        a_g=1; b_g=1; c_g=1; #10;
        $finish;
    end
endmodule

subractor/full_sub/full_output.vcd
$date
	Sat Apr 11 20:26:48 2026
$end
$version
	Icarus Verilog
$end
$timescale
	1s
$end
$scope module full_tb $end
$var wire 1 ! diff_g $end
$var wire 1 " diff_d $end
$var wire 1 # diff_b $end
$var wire 1 $ bor_g $end
$var wire 1 % bor_d $end
$var wire 1 & bor_b $end
$var reg 1 ' a_b $end
$var reg 1 ( a_d $end
$var reg 1 ) a_g $end
$var reg 1 * b_b $end
$var reg 1 + b_d $end
$var reg 1 , b_g $end
$var reg 1 - c_b $end
$var reg 1 . c_d $end
$var reg 1 / c_g $end
$scope module dut_b $end
$var wire 1 ' a $end
$var wire 1 * b $end
$var wire 1 - c $end
$var reg 1 & bor $end
$var reg 1 # diff $end
$upscope $end
$scope module dut_d $end
$var wire 1 ( a $end
$var wire 1 + b $end
$var wire 1 % bor $end
$var wire 1 . c $end
$var wire 1 " diff $end
$upscope $end
$scope module dut_g $end
$var wire 1 ) a $end
$var wire 1 , b $end
$var wire 1 $ bor $end
$var wire 1 / c $end
$var wire 1 ! diff $end
$var wire 1 0 t1 $end
$var wire 1 1 t2 $end
$var wire 1 2 t3 $end
$var wire 1 3 t4 $end
$var wire 1 4 t5 $end
$upscope $end
$upscope $end
$enddefinitions $end
$comment Show the parameter values. $end
$dumpall
$end
#0
$dumpvars
x4
x3
x2
x1
x0
x/
x.
0-
x,
x+
0*
x)
x(
0'
0&
x%
x$
0#
x"
x!
$end
#10
1&
1#
1-
#20
0-
1*
#30
0#
1-
#40
0&
1#
0-
0*
1'
#50
0#
1-
#60
0%
0"
0.
1+
1(
#70
1%
1"
1.
#80
0%
0"
0.
0+
0(
#90
1%
1"
1.
#100
0.
1+
#110
0"
1.
#120
0%
1"
0.
0+
1(
#130
0"
1.
#140
0.
1+
#150
1%
1"
1.
#160
0$
13
0!
04
02
00
11
0/
0,
0)
#170
1$
1!
14
1/
#180
03
04
10
12
0/
1,
#190
0!
1/
#200
0$
1!
02
01
0/
0,
1)
#210
0!
1/
#220
13
00
0/
1,
#230
1$
1!
14
1/
