subractor/full_sub/full.v
module full (
    a,b,c,diff,bor
);
    input a,b,c;
    output reg diff,bor;

    always @(*) begin
        diff = a^b^c;
        bor = ~a&b|~(a^b)&c;
    end
endmodule

subractor/full_sub/full_tb.v
module full_tb;
    reg a,b,c;
    wire diff,bor;

    full dut(.a(a),.b(b),.c(c),.diff(diff),.bor(bor));

    initial begin
        $dumpfile("full_output.vcd");
        $dumpvars(0,full_tb);
        $monitor("a=%b  b=%b  c=%b  diff=%b   bor=%b", a,b,c,diff,bor);

        a=0; b=0; c=0; #10; 
        a=0; b=0; c=1; #10;   
        a=0; b=1; c=0; #10;   
        a=0; b=1; c=1; #10;    
        a=1; b=0; c=0; #10;  
        a=1; b=0; c=1; #10;   
        a=1; b=1; c=0; #10;   
        a=1; b=1; c=1; #10; 

        $finish;
    end
endmodule

subractor/full_sub/full_output.vcd
$date
	Sat Apr 11 16:25:04 2026
$end
$version
	Icarus Verilog
$end
$timescale
	1s
$end
$scope module full_tb $end
$var wire 1 ! diff $end
$var wire 1 " bor $end
$var reg 1 # a $end
$var reg 1 $ b $end
$var reg 1 % c $end
$scope module dut $end
$var wire 1 # a $end
$var wire 1 $ b $end
$var wire 1 % c $end
$var reg 1 " bor $end
$var reg 1 ! diff $end
$upscope $end
$upscope $end
$enddefinitions $end
$comment Show the parameter values. $end
$dumpall
$end
#0
$dumpvars
0%
0$
0#
0"
0!
$end
#10
1"
1!
1%
#20
0%
1$
#30
0!
1%
#40
0"
1!
0%
0$
1#
#50
0!
1%
#60
0%
1$
#70
1"
1!
1%
