mux/four_one/four_one.v
module four_one (a,b,c,d,,sel,y);
    input a,b,c,d;
    input [1:0] sel;
    output reg  y;
 
always @(*) begin
    case (sel)
        2'b00: y = a;
        2'b01: y = b;
        2'b10: y = c;
        2'b11: y = d;
        default: y = 1'b0;
    endcase
end

endmodule

mux/four_one/four_one_tb.v
 
module four_one_tb;

    reg  a, b, c, d;
    reg  [1:0] sel;
    wire y;

     four_one dut (
        .a(a), .b(b), .c(c), .d(d),
        .sel(sel), .y(y)
        
    );

    initial begin

        $dumpfile("wave.vcd");
        $dumpvars(0, four_one_tb);
        $monitor("Time=%0t | sel=%b | a=%b b=%b c=%b d=%b y=%b",$time, sel, a, b, c, d, y);
         
         a = 0; b = 1; c = 0; d = 1;

        sel = 2'b00; #10;
        sel = 2'b01; #10;
        sel = 2'b10; #10;
        sel = 2'b11; #10;

         a = 1; b = 0; c = 1; d = 0;

        sel = 2'b00; #10;
        sel = 2'b01; #10;
        sel = 2'b10; #10;
        sel = 2'b11; #10;

        $finish;
    end

endmodule

mux/four_one/wave.vcd
$date
	Tue Apr 21 21:16:24 2026
$end
$version
	Icarus Verilog
$end
$timescale
	1s
$end
$scope module four_one_tb $end
$var wire 1 ! y $end
$var reg 1 " a $end
$var reg 1 # b $end
$var reg 1 $ c $end
$var reg 1 % d $end
$var reg 2 & sel [1:0] $end
$scope module dut $end
$var wire 1 " a $end
$var wire 1 # b $end
$var wire 1 $ c $end
$var wire 1 % d $end
$var wire 2 ' sel [1:0] $end
$var reg 1 ! y $end
$upscope $end
$upscope $end
$enddefinitions $end
$comment Show the parameter values. $end
$dumpall
$end
#0
$dumpvars
b0 '
b0 &
1%
0$
1#
0"
0!
$end
#10
1!
b1 &
b1 '
#20
0!
b10 &
b10 '
#30
1!
b11 &
b11 '
#40
b0 &
b0 '
0%
1$
0#
1"
#50
0!
b1 &
b1 '
#60
1!
b10 &
b10 '
#70
0!
b11 &
b11 '
