subractor/half_sub/half.v
module half_dataflow(
    a,b,diff,bor
);
    input a,b;
    output diff,bor;

    assign diff = a^b;
    assign bor = ~a&b;
endmodule

module half_behavioural (
    a,b,diff,bor
);
    input a,b;
    output reg diff,bor;
    always @(*) begin
        diff = a^b;
        bor = ~a&b;
    end
endmodule

module half_gatelevel (
    a,b,diff,bor
);
    input a,b;
    output diff,bor;
    wire n;

    xor g1(diff,a,b);
    not g2(n,a);
    and g3(bor,n,b);
endmodule

subractor/half_sub/half_tb.v
module half_tb;
    reg a_b,b_b,a_g,b_g,a_d,b_d;
    wire  bor_b,diff_b,bor_g,diff_g,bor_d,diff_d;

    half_dataflow dut_dataflow(.a(a_b),.b(b_b),.diff(diff_b),.bor(bor_b));
    half_behavioural dut_behavioural(.a(a_g),.b(b_g),.diff(diff_g),.bor(bor_g));
    half_gatelevel dut_gatelevel(.a(a_d),.b(b_d),.diff(diff_d),.bor(bor_d));

    initial begin
        $dumpfile("half_output.vcd");
        $dumpvars(0,half_tb);

        $monitor("behavioural: a=%b   b=%b   diff=%b   borrow=%b", a_b,b_b,diff_b,bor_b);
        a_b=0; b_b=0; #10;
        a_b=0; b_b=1; #10;
        a_b=1; b_b=0; #10;
        a_b=1; b_b=1; #10;

        $monitor("gate-level: a=%b   b=%b   diff=%b   borrow=%b", a_g,b_g,diff_g,bor_g);
        a_g=0; b_g=0; #10;
        a_g=0; b_g=1; #10;
        a_g=1; b_g=0; #10;
        a_g=1; b_g=1; #10;

        $monitor("dataflow: a=%b   b=%b   diff=%b   borrow=%b", a_d,b_d,diff_d,bor_d);
        a_d=0; b_d=0; #10;
        a_d=0; b_d=1; #10;
        a_d=1; b_d=0; #10;
        a_d=1; b_d=1; #10;
        $finish;
    end
endmodule

subractor/half_sub/half_output.vcd
$date
	Sat Apr 11 20:04:04 2026
$end
$version
	Icarus Verilog
$end
$timescale
	1s
$end
$scope module half_tb $end
$var wire 1 ! diff_g $end
$var wire 1 " diff_d $end
$var wire 1 # diff_b $end
$var wire 1 $ bor_g $end
$var wire 1 % bor_d $end
$var wire 1 & bor_b $end
$var reg 1 ' a_b $end
$var reg 1 ( a_d $end
$var reg 1 ) a_g $end
$var reg 1 * b_b $end
$var reg 1 + b_d $end
$var reg 1 , b_g $end
$scope module dut_behavioural $end
$var wire 1 ) a $end
$var wire 1 , b $end
$var reg 1 $ bor $end
$var reg 1 ! diff $end
$upscope $end
$scope module dut_dataflow $end
$var wire 1 ' a $end
$var wire 1 * b $end
$var wire 1 & bor $end
$var wire 1 # diff $end
$upscope $end
$scope module dut_gatelevel $end
$var wire 1 ( a $end
$var wire 1 + b $end
$var wire 1 % bor $end
$var wire 1 " diff $end
$var wire 1 - n $end
$upscope $end
$upscope $end
$enddefinitions $end
$comment Show the parameter values. $end
$dumpall
$end
#0
$dumpvars
x-
x,
x+
0*
x)
x(
0'
0&
x%
x$
0#
x"
x!
$end
#10
1#
1&
1*
#20
0&
0*
1'
#30
0#
1*
#40
0$
0!
0,
0)
#50
1$
1!
1,
#60
0$
0,
1)
#70
0!
1,
#80
0%
0"
1-
0+
0(
#90
1"
1%
1+
#100
0%
0-
0+
1(
#110
0"
1+
