mux/eight_one/eight_one.v
module eight_one (
    input [7:0] i,
    input [2:0] s,
    output y
);
    assign y = i[s];
    
endmodule

mux/eight_one/eight_one_tb.v
module eight_one_tb();
    reg [7:0] i;
    reg [2:0] s;
    wire y;
    integer k;
    eight_one dut(.i(i),.s(s),.y(y));
    initial begin
        $dumpfile("wave.vcd");
        $dumpvars(0,eight_one_tb);
        $monitor("i = %b  s = %b  y = %b",i,s,y);

        i = 8'b00001101;
        s = 3'b000;

        for (k =0 ;k<8 ;k++ ) begin
            s = k;
            #10;
        end

        $finish;

    end
    endmodule

mux/eight_one/wave.vcd
$date
	Tue Apr 21 21:33:45 2026
$end
$version
	Icarus Verilog
$end
$timescale
	1s
$end
$scope module eight_one_tb $end
$var wire 1 ! y $end
$var reg 8 " i [7:0] $end
$var reg 3 # s [2:0] $end
$var integer 32 $ k [31:0] $end
$scope module dut $end
$var wire 8 % i [7:0] $end
$var wire 3 & s [2:0] $end
$var wire 1 ! y $end
$upscope $end
$upscope $end
$enddefinitions $end
$comment Show the parameter values. $end
$dumpall
$end
#0
$dumpvars
b0 &
b1101 %
b0 $
b0 #
b1101 "
1!
$end
#10
0!
b1 #
b1 &
b1 $
#20
1!
b10 #
b10 &
b10 $
#30
b11 #
b11 &
b11 $
#40
0!
b100 #
b100 &
b100 $
#50
b101 #
b101 &
b101 $
#60
b110 #
b110 &
b110 $
#70
b111 #
b111 &
b111 $
#80
b1000 $
