mux/sixteen_one/sixteen_one.v
module sixteen_one (
    input [15:0] i,
    input [3:0] s,
    output y
); 
    assign y = i[s];
    
endmodule

mux/sixteen_one/sixteen_one_tb.v
module sixteen_one_tb();
    reg [15:0] i;
    reg [3:0] s;
    wire y;
    integer k;
    sixteen_one dut(.i(i),.s(s),.y(y));
    initial begin
        $dumpfile("wave.vcd");
        $dumpvars(0,sixteen_one_tb);
        $monitor("i = %b  s = %b  y = %b",i,s,y);

        i = 16'b0000110101001101;
        s = 4'b0000;

        for (k =0 ;k<16 ;k++ ) begin
            s = k;
            #10;
        end

        $finish;

    end
    endmodule

mux/sixteen_one/wave.vcd
$date
	Tue Apr 21 21:41:49 2026
$end
$version
	Icarus Verilog
$end
$timescale
	1s
$end
$scope module sixteen_one_tb $end
$var wire 1 ! y $end
$var reg 16 " i [15:0] $end
$var reg 4 # s [3:0] $end
$var integer 32 $ k [31:0] $end
$scope module dut $end
$var wire 16 % i [15:0] $end
$var wire 4 & s [3:0] $end
$var wire 1 ! y $end
$upscope $end
$upscope $end
$enddefinitions $end
$comment Show the parameter values. $end
$dumpall
$end
#0
$dumpvars
b0 &
b110101001101 %
b0 $
b0 #
b110101001101 "
1!
$end
#10
0!
b1 #
b1 &
b1 $
#20
1!
b10 #
b10 &
b10 $
#30
b11 #
b11 &
b11 $
#40
0!
b100 #
b100 &
b100 $
#50
b101 #
b101 &
b101 $
#60
1!
b110 #
b110 &
b110 $
#70
0!
b111 #
b111 &
b111 $
#80
1!
b1000 #
b1000 &
b1000 $
#90
0!
b1001 #
b1001 &
b1001 $
#100
1!
b1010 #
b1010 &
b1010 $
#110
b1011 #
b1011 &
b1011 $
#120
0!
b1100 #
b1100 &
b1100 $
#130
b1101 #
b1101 &
b1101 $
#140
b1110 #
b1110 &
b1110 $
#150
b1111 #
b1111 &
b1111 $
#160
b10000 $
