different_modelling/and/and_gate.v
module behavioural (
    input a,b,output reg y
);
    always @(a or b) begin
        y = a&b;
    end
endmodule

module dataflow (
    input a,b,output y
);
    assign y = a&b;
endmodule

module gatelevel (
    input a,b,output y
);
    and g1(y,a,b);
endmodule

module switchlevel (
    input a,b,output y
);
    supply0 gnd;
    supply1 vdd;
    wire n,y1;

    pmos p1(y1,vdd,a);
    pmos p2(y1,vdd,b);

    nmos n1(n,gnd,a);
    nmos n2(y1,n,b);

    pmos p3(y,vdd,y1);
    nmos n3(y,gnd,y1);

endmodule

different_modelling/and/and_tb.v
module and_tb();
    reg b_a,b_b,d_a,d_b,g_a,g_b,s_a,s_b;
    wire b_y,d_y,g_y,s_y;

    behavioural dut(.a(b_a),.b(b_b),.y(b_y));
    dataflow uut(.a(d_a),.b(d_b),.y(d_y));
    gatelevel dut1(.a(g_a),.b(g_b),.y(g_y));
    switchlevel uut1(.a(s_a),.b(s_b),.y(s_y));

    initial begin
        $dumpfile("wave.vcd");
        $dumpvars(0,and_tb);
        $monitor("and behavioural a=%b  b=%b  y=%b",b_a,b_b,b_y);

        b_a=0; b_b=0;#10;
        b_a=0; b_b=1;#10;
        b_a=1; b_b=0;#10;
        b_a=1; b_b=1;#10;
        $monitor("and dataflow a=%b  b=%b  y=%b",d_a,d_b,d_y);
        d_a=0; d_b=0;#10;
        d_a=0; d_b=1;#10;
        d_a=1; d_b=0;#10;
        d_a=1; d_b=1;#10;
        $monitor("and gatelevel a=%b  b=%b  y=%b",g_a,g_b,g_y);
        g_a=0; g_b=0;#10;
        g_a=0; g_b=1;#10;
        g_a=1; g_b=0;#10;
        g_a=1; g_b=1;#10;
        $monitor("and switchlevel a=%b  b=%b  y=%b",s_a,s_b,s_y);
        s_a=0; s_b=0;#10;
        s_a=0; s_b=1;#10;
        s_a=1; s_b=0;#10;
        s_a=1; s_b=1;#10;
        $finish;
    end
endmodule

different_modelling/and/wave.vcd
$date
	Sat Apr 11 16:06:52 2026
$end
$version
	Icarus Verilog
$end
$timescale
	1s
$end
$scope module and_tb $end
$var wire 1 ! s_y $end
$var wire 1 " g_y $end
$var wire 1 # d_y $end
$var wire 1 $ b_y $end
$var reg 1 % b_a $end
$var reg 1 & b_b $end
$var reg 1 ' d_a $end
$var reg 1 ( d_b $end
$var reg 1 ) g_a $end
$var reg 1 * g_b $end
$var reg 1 + s_a $end
$var reg 1 , s_b $end
$scope module dut $end
$var wire 1 % a $end
$var wire 1 & b $end
$var reg 1 $ y $end
$upscope $end
$scope module dut1 $end
$var wire 1 ) a $end
$var wire 1 * b $end
$var wire 1 " y $end
$upscope $end
$scope module uut $end
$var wire 1 ' a $end
$var wire 1 ( b $end
$var wire 1 # y $end
$upscope $end
$scope module uut1 $end
$var wire 1 + a $end
$var wire 1 , b $end
$var wire 1 - gnd $end
$var wire 1 . n $end
$var wire 1 / vdd $end
$var wire 1 ! y $end
$var wire 1 0 y1 $end
$upscope $end
$upscope $end
$enddefinitions $end
$comment Show the parameter values. $end
$dumpall
$end
#0
$dumpvars
x0
1/
x.
0-
x,
x+
x*
x)
x(
x'
0&
0%
0$
x#
x"
x!
$end
#10
1&
#20
0&
1%
#30
1$
1&
#40
0#
0(
0'
#50
1(
#60
0(
1'
#70
1#
1(
#80
0"
0*
0)
#90
1*
#100
0*
1)
#110
1"
1*
#120
0,
0!
10
z.
0+
#130
1,
#140
0,
0!
10
0.
1+
#150
1!
00
1,
