adder/half_adder/half_adder.v
module half_adder_by_gatelevel (
    a,b,sum,carry
);
    output sum,carry;
    input a,b;

    xor g1(sum,a,b);
    and g2(carry,a,b);
endmodule

module half_adder_by_dataflow (
    a,b,sum,carry
);
    output sum,carry;
    input a,b;

    assign sum = a^b;
    assign carry = a&b;
endmodule

module half_adder_by_behavioural (
    a,b,sum,carry
);
    output reg sum,carry;
    input a,b;

    always @(*) begin
        sum = a^b;
        carry =a&b;
    end
    
endmodule

adder/half_adder/half_adder_tb.v
module half_adder_tb;
    reg a_g,a_d,a_b,b_g,b_b,b_d;
    wire sum_g,sum_d,sum_b,carry_g,carry_d,carry_b;

    half_adder_by_gatelevel dut1(.a(a_g),.b(b_g),.sum(sum_g),.carry(carry_g));
    half_adder_by_dataflow dut2(.a(a_d),.b(b_d),.sum(sum_d),.carry(carry_d));
    half_adder_by_behavioural dut3(.a(a_b),.b(b_b),.sum(sum_b),.carry(carry_b));

    initial begin
        $dumpfile("half_adder.vcd");
        $dumpvars(0,half_adder_tb);
        
        $monitor(" half_adder_by_gatelevel: a=%b  b=%b  sum=%b  carry=%b",a_g,b_g,sum_g,carry_g);
        a_g = 0; b_g = 0; #10;
        a_g = 0; b_g = 1; #10;
        a_g = 1; b_g = 0; #10;
        a_g = 1; b_g = 1; #10;

        $monitor(" half_adder_by_dataflow: a=%b  b=%b  sum=%b  carry=%b",a_d,b_d,sum_d,carry_d);
        a_d = 0; b_d = 0; #10;
        a_d = 0; b_d = 1; #10;
        a_d = 1; b_d = 0; #10;
        a_d = 1; b_d = 1; #10;

        $monitor(" half_adder_by_behavioural: a=%b  b=%b  sum=%b  carry=%b",a_b,b_b,sum_b,carry_b);
        a_b = 0; b_b = 0; #10;
        a_b = 0; b_b = 1; #10;
        a_b = 1; b_b = 0; #10;
        a_b = 1; b_b = 1; #10;

        $finish;

    end

endmodule

adder/half_adder/half_adder.vcd
$date
	Sat Apr 11 16:45:13 2026
$end
$version
	Icarus Verilog
$end
$timescale
	1s
$end
$scope module half_adder_tb $end
$var wire 1 ! sum_g $end
$var wire 1 " sum_d $end
$var wire 1 # sum_b $end
$var wire 1 $ carry_g $end
$var wire 1 % carry_d $end
$var wire 1 & carry_b $end
$var reg 1 ' a_b $end
$var reg 1 ( a_d $end
$var reg 1 ) a_g $end
$var reg 1 * b_b $end
$var reg 1 + b_d $end
$var reg 1 , b_g $end
$scope module dut1 $end
$var wire 1 ) a $end
$var wire 1 , b $end
$var wire 1 $ carry $end
$var wire 1 ! sum $end
$upscope $end
$scope module dut2 $end
$var wire 1 ( a $end
$var wire 1 + b $end
$var wire 1 % carry $end
$var wire 1 " sum $end
$upscope $end
$scope module dut3 $end
$var wire 1 ' a $end
$var wire 1 * b $end
$var reg 1 & carry $end
$var reg 1 # sum $end
$upscope $end
$upscope $end
$enddefinitions $end
$comment Show the parameter values. $end
$dumpall
$end
#0
$dumpvars
0,
x+
x*
0)
x(
x'
x&
x%
0$
x#
x"
0!
$end
#10
1!
1,
#20
0,
1)
#30
0!
1$
1,
#40
0"
0%
0+
0(
#50
1"
1+
#60
0+
1(
#70
0"
1%
1+
#80
0&
0#
0*
0'
#90
1#
1*
#100
0*
1'
#110
1&
0#
1*
