adder/full_adder/full_adder.v
module full_adder (
    input a,
    input b,
    input c,
    output y,
    output Cout
);
   
    assign y = a^b^c;
    assign Cout = (a&b)|(a&c)|(b&c);
endmodule

adder/full_adder/full_adder_tb.v
module full_adder_tb();
    reg a,b,c;
    wire Cout,y;

    full_adder uut(
        .a(a),
        .b(b),
        .c(c),
        .y(y),
        .Cout(Cout)
    
    );
    initial begin

        $dumpfile("wave.vcd");   
        $dumpvars(0, full_adder_tb);
        $monitor("Time=%0t | a=%b b=%b c=%b -> y=%b Cout=%b", $time, a, b, c, y, Cout);
        a=0; b=0; c=0; #10; 
        a=0; b=0; c=1; #10;   
        a=0; b=1; c=0; #10;   
        a=0; b=1; c=1; #10;    
        a=1; b=0; c=0; #10;  
        a=1; b=0; c=1; #10;   
        a=1; b=1; c=0; #10;   
        a=1; b=1; c=1; #10;   

        $finish;
    end
endmodule

adder/full_adder/wave.vcd
$date
	Sat Apr 11 16:18:14 2026
$end
$version
	Icarus Verilog
$end
$timescale
	1s
$end
$scope module full_adder_tb $end
$var wire 1 ! y $end
$var wire 1 " Cout $end
$var reg 1 # a $end
$var reg 1 $ b $end
$var reg 1 % c $end
$scope module uut $end
$var wire 1 " Cout $end
$var wire 1 # a $end
$var wire 1 $ b $end
$var wire 1 % c $end
$var wire 1 ! y $end
$upscope $end
$upscope $end
$enddefinitions $end
$comment Show the parameter values. $end
$dumpall
$end
#0
$dumpvars
0%
0$
0#
0"
0!
$end
#10
1!
1%
#20
0%
1$
#30
1"
0!
1%
#40
0"
1!
0%
0$
1#
#50
1"
0!
1%
#60
0%
1$
#70
1!
1%
