adder/full_adder/full_adder.v
module full_adder_dataflow(
    input a,
    input b,
    input c,
    output y,
    output Cout
);
   
    assign y = a^b^c;
    assign Cout = (a&b)|(a&c)|(b&c);
endmodule

module full_adder_behavioural (
    sum,carry,a,b,c
);
    input a,b,c;
    output reg sum,carry;
    always @(*) begin
        sum=a^b^c;
        carry=(a&b)|(a&c)|(b&c);
    end
endmodule

module full_adder_gatelevel (
    output sum,carry,input a,b,c
);
    wire t1,t2,t3,t4,t5;
    xor g1(t1,a,b);
    xor g2(sum,t1,c);
    and g3(t2,a,b);
    and g4(t3,b,c);
    and g5(t4,a,c);
    or g6(t5,t2,t3);
    or g7(carry,t4,t5);

endmodule

adder/full_adder/full_adder_tb.v
module full_adder_tb();
    reg a_d,b_d,c_d,a_b,b_b,c_b,a_g,b_g,c_g;
    wire Cout_d,y_d,Cout_b,sum_b,Cout_g,sum_g;

    full_adder_dataflow uut_d(
        .a(a_d),
        .b(b_d),
        .c(c_d),
        .y(y_d),
        .Cout(Cout_d)
    
    );
    full_adder_behavioural uut_b(
        .a(a_b),
        .b(b_b),
        .c(c_b),
        .sum(sum_b),
        .carry(Cout_b)
    
    );
    full_adder_gatelevel uut_g(
        .a(a_g),
        .b(b_g),
        .c(c_g),
        .sum(sum_g),
        .carry(Cout_g)
    
    );
    initial begin

        $dumpfile("wave.vcd");   
        $dumpvars(0, full_adder_tb);
        $monitor("dataflow  Time=%0t | a=%b b=%b c=%b -> y=%b Cout=%b", $time, a_d, b_d, c_d, y_d, Cout_d);
        a_d=0; b_d=0; c_d=0; #10; 
        a_d=0; b_d=0; c_d=1; #10;   
        a_d=0; b_d=1; c_d=0; #10;   
        a_d=0; b_d=1; c_d=1; #10;    
        a_d=1; b_d=0; c_d=0; #10;  
        a_d=1; b_d=0; c_d=1; #10;   
        a_d=1; b_d=1; c_d=0; #10;   
        a_d=1; b_d=1; c_d=1; #10;   


        $monitor("behavioural  Time=%0t | a=%b b=%b c=%b -> sum=%b carry=%b", $time, a_b, b_b, c_b, sum_b, Cout_b);
        a_b=0; b_b=0; c_b=0; #10;
        a_b=0; b_b=0; c_b=1; #10;
        a_b=0; b_b=1; c_b=0; #10;
        a_b=0; b_b=1; c_b=1; #10;
        a_b=1; b_b=0; c_b=0; #10;
        a_b=1; b_b=0; c_b=1; #10;
        a_b=1; b_b=1; c_b=0; #10;
        a_b=1; b_b=1; c_b=1; #10;
        
        $monitor("gatelevel  Time=%0t | a=%b b=%b c=%b -> sum=%b carry=%b", $time, a_g, b_g, c_g, sum_g, Cout_g);
        a_g=0; b_g=0; c_g=0; #10;
        a_g=0; b_g=0; c_g=1; #10;
        a_g=0; b_g=1; c_g=0; #10;
        a_g=0; b_g=1; c_g=1; #10;
        a_g=1; b_g=0; c_g=0; #10;
        a_g=1; b_g=0; c_g=1; #10;
        a_g=1; b_g=1; c_g=0; #10;
        a_g=1; b_g=1; c_g=1; #10;
        

        $finish;
    end
endmodule

adder/full_adder/wave.vcd
$date
	Sat Apr 11 19:51:07 2026
$end
$version
	Icarus Verilog
$end
$timescale
	1s
$end
$scope module full_adder_tb $end
$var wire 1 ! y_d $end
$var wire 1 " sum_g $end
$var wire 1 # sum_b $end
$var wire 1 $ Cout_g $end
$var wire 1 % Cout_d $end
$var wire 1 & Cout_b $end
$var reg 1 ' a_b $end
$var reg 1 ( a_d $end
$var reg 1 ) a_g $end
$var reg 1 * b_b $end
$var reg 1 + b_d $end
$var reg 1 , b_g $end
$var reg 1 - c_b $end
$var reg 1 . c_d $end
$var reg 1 / c_g $end
$scope module uut_b $end
$var wire 1 ' a $end
$var wire 1 * b $end
$var wire 1 - c $end
$var reg 1 & carry $end
$var reg 1 # sum $end
$upscope $end
$scope module uut_d $end
$var wire 1 % Cout $end
$var wire 1 ( a $end
$var wire 1 + b $end
$var wire 1 . c $end
$var wire 1 ! y $end
$upscope $end
$scope module uut_g $end
$var wire 1 ) a $end
$var wire 1 , b $end
$var wire 1 / c $end
$var wire 1 $ carry $end
$var wire 1 " sum $end
$var wire 1 0 t1 $end
$var wire 1 1 t2 $end
$var wire 1 2 t3 $end
$var wire 1 3 t4 $end
$var wire 1 4 t5 $end
$upscope $end
$upscope $end
$enddefinitions $end
$comment Show the parameter values. $end
$dumpall
$end
#0
$dumpvars
x4
x3
x2
x1
x0
x/
0.
x-
x,
0+
x*
x)
0(
x'
x&
0%
x$
x#
x"
0!
$end
#10
1!
1.
#20
0.
1+
#30
1%
0!
1.
#40
0%
1!
0.
0+
1(
#50
1%
0!
1.
#60
0.
1+
#70
1!
1.
#80
0&
0#
0-
0*
0'
#90
1#
1-
#100
0-
1*
#110
1&
0#
1-
#120
0&
1#
0-
0*
1'
#130
1&
0#
1-
#140
0-
1*
#150
1#
1-
#160
0$
04
0"
02
00
01
03
0/
0,
0)
#170
1"
1/
#180
10
0/
1,
#190
1$
14
0"
12
1/
#200
0$
04
1"
02
0/
0,
1)
#210
1$
0"
13
1/
#220
14
03
00
11
0/
1,
#230
1"
12
13
1/
